colab_notebook_utils/__init__.py
colab_notebook_utils/workspace.py
colab_notebook_utils-1.0.1.dist-info/LICENSE
colab_notebook_utils-1.0.1.dist-info/METADATA
colab_notebook_utils-1.0.1.dist-info/WHEEL
colab_notebook_utils-1.0.1.dist-info/top_level.txt
colab_notebook_utils-1.0.1.dist-info/RECORD
