Metadata-Version: 2.1
Name: colab-notebook-utils
Version: 1.0.1
Summary: Usefull tools for dealing with colab notebooks
Home-page: https://github.com/tboulet/Colab-Utils
Author: =?utf-8?q?Timoth=C3=A9_Boulet?=
Author-email: timotheboulet0@gmail.com
License: MIT
License-File: LICENSE
